{
  "source_title": "Por que nossa clínica é a escolha ideal?",
  "source_url": "https://drabrunasilvestrini.com.br/#quem-somos",
  "caption": "Por que escolher a nossa clínica para o seu cuidado facial? 💎\n\n✔️ Excelência: Compromisso com resultados impecáveis.\n✔️ Segurança: Protocolos rigorosos e a melhor tecnologia do mercado.\n✔️ Inovação: Técnicas modernas e produtos premium de última geração.\n✔️ Exclusividade: Tratamentos 100% personalizados com mapeamento individualizado do seu rosto.\n\nVenha viver essa experiência!\n\n📲 Agende sua avaliação pelo WhatsApp: (11) 99550-5765\nOu clique no link da bio!",
  "hashtags": [
    "#DraBrunaSilvestrini",
    "#ClinicaEsteticaSP",
    "#EsteticaPremium",
    "#Seguranca",
    "#InovacaoNaEstetica",
    "#AtendimentoExclusivo"
  ],
  "image_prompt": "",
  "image_url": "https://drabrunasilvestrini.com.br/assets/hero_modern_interactive_face_1770921982241.png",
  "alt_text": "Rosto interativo e moderno representando tecnologia e exclusividade",
  "posting_suggestion": "Postar no Feed às 12h",
  "story_idea": "Mostre os produtos premium que você utiliza.",
  "disclaimer": "Resultados variam. Avaliação individual é indispensável.",
  "is_video": false,
  "video_script": ""
}