{
  "source_title": "Nossos Procedimentos",
  "source_url": "https://drabrunasilvestrini.com.br/#procedimentos",
  "caption": "Você sabia que a harmonização facial vai muito além de preenchimentos? Ela envolve um planejamento cuidadoso para equilibrar proporções, suavizar linhas de expressão e devolver o viço da sua pele. Trabalhamos com Toxina Botulínica, Fios de Sustentação, Bioestimuladores e muito mais, sempre priorizando resultados elegantes e sutis.\n\n📲 Agende sua avaliação pelo WhatsApp: (11) 99550-5765\nOu clique no link da bio!",
  "hashtags": [
    "#DraBrunaSilvestrini",
    "#ProcedimentosEsteticos",
    "#ToxinaBotulinica",
    "#PreenchimentoFacial",
    "#Bioestimuladores",
    "#EsteticaAvancada",
    "#Rejuvenescimento",
    "#Beleza",
    "#SaudeDaPele"
  ],
  "image_prompt": "Fotografia hiper-realista de um rosto feminino com pele perfeita, natural e iluminada, sendo examinada delicadamente por mãos com luvas de procedimento brancas, ambiente clínico de luxo, 85mm, 4k",
  "alt_text": "Paciente recebendo cuidados estéticos no rosto.",
  "posting_suggestion": "Postar no Feed às 12h",
  "story_idea": "Abra uma caixinha de perguntas sobre os procedimentos que a clínica oferece.",
  "disclaimer": "Resultados variam. Avaliação individual é indispensável.",
  "is_video": false,
  "video_script": ""
}